streamsnapper/__init__.py
streamsnapper/core.py
streamsnapper/data.py
streamsnapper/exceptions.py
streamsnapper/helpers.py
streamsnapper/logger.py
streamsnapper/models/__init__.py
streamsnapper/models/audio.py
streamsnapper/models/extractor.py
streamsnapper/models/subtitle.py
streamsnapper/models/video.py
streamsnapper/py.typed
streamsnapper/scraper.py
streamsnapper/utils.py
streamsnapper-0.4.1.dist-info/WHEEL
streamsnapper-0.4.1.dist-info/METADATA
streamsnapper-0.4.1.dist-info/RECORD
