Metadata-Version: 2.4
Name: streamsnapper
Version: 0.4.1
Summary: Extract and analyze YouTube video streams with intelligent quality selection, language fallback, and comprehensive metadata retrieval
Keywords: stream,snapper,scraper,downloader,merger,youtube,youtube-music,media,video,audio
Author: henrique-coder
Author-email: henrique-coder <henriquemoreira10fk@gmail.com>
License-Expression: MIT
Classifier: Development Status :: 4 - Beta
Classifier: Intended Audience :: Developers
Classifier: License :: OSI Approved :: MIT License
Classifier: Operating System :: OS Independent
Classifier: Programming Language :: Python :: 3 :: Only
Classifier: Programming Language :: Python :: 3.10
Classifier: Programming Language :: Python :: 3.11
Classifier: Programming Language :: Python :: 3.12
Classifier: Programming Language :: Python :: 3.13
Classifier: Programming Language :: Python :: 3.14
Classifier: Programming Language :: Python :: Implementation :: CPython
Classifier: Programming Language :: Python :: Implementation :: PyPy
Classifier: Topic :: Internet
Classifier: Topic :: Internet :: WWW/HTTP
Classifier: Topic :: Multimedia
Classifier: Topic :: Multimedia :: Video
Classifier: Topic :: Multimedia :: Sound/Audio
Classifier: Topic :: Software Development :: Libraries
Classifier: Topic :: Software Development :: Libraries :: Python Modules
Classifier: Topic :: Utilities
Classifier: Typing :: Typed
Requires-Dist: curl-cffi>=0.14.0
Requires-Dist: loguru>=0.7.3
Requires-Dist: pydantic>=2.12.5
Requires-Dist: yt-dlp[default]>=2025.12.8
Requires-Python: >=3.10
Project-URL: Changelog, https://github.com/henrique-coder/streamsnapper/releases
Project-URL: Documentation, https://github.com/henrique-coder/streamsnapper/blob/main/README.md
Project-URL: Homepage, https://github.com/henrique-coder/streamsnapper
Project-URL: Issues, https://github.com/henrique-coder/streamsnapper/issues
Project-URL: Repository, https://github.com/henrique-coder/streamsnapper
